Metadata-Version: 2.1
Name: django-uniauth
Version: 1.4.1
Summary: A Django app for managing CAS and custom user authentication.
Home-page: https://github.com/lgoodridge/django-uniauth
Author: Lance Goodridge
Author-email: ldgoodridge95@gmail.com
License: LGPLv3
Keywords: django,auth,authentication,cas,sso,single sign-on
Platform: UNKNOWN
Classifier: Development Status :: 5 - Production/Stable
Classifier: Framework :: Django
Classifier: Framework :: Django :: 1.11
Classifier: Framework :: Django :: 2
Classifier: Framework :: Django :: 3
Classifier: Framework :: Django :: 4
Classifier: Intended Audience :: Developers
Classifier: License :: OSI Approved :: GNU Lesser General Public License v3 (LGPLv3)
Classifier: Natural Language :: English
Classifier: Operating System :: OS Independent
Classifier: Programming Language :: Python
Classifier: Programming Language :: Python :: 2
Classifier: Programming Language :: Python :: 3
Requires-Python: >=2.7, !=3.0.*, !=3.1.*, !=3.2.*, !=3.3.*, !=3.4.*
Requires-Dist: Django (>=1.11)
Requires-Dist: python-cas (>=1.4.0)
Requires-Dist: djangorestframework-simplejwt (>=4.1.0)
Requires-Dist: mock ; python_version<='3.2'
